okb/__init__.py
okb/cli.py
okb/config.py
okb/data/init.sql
okb/http_server.py
okb/ingest.py
okb/llm/__init__.py
okb/llm/base.py
okb/llm/cache.py
okb/llm/filter.py
okb/llm/providers.py
okb/local_embedder.py
okb/mcp_server.py
okb/migrate.py
okb/migrations/0001.initial-schema.sql
okb/migrations/0002.sync-state.sql
okb/migrations/0003.structured-fields.sql
okb/migrations/0004.tokens.sql
okb/migrations/0005.database-metadata.sql
okb/migrations/0006.llm-cache.sql
okb/modal_embedder.py
okb/modal_llm.py
okb/plugins/__init__.py
okb/plugins/base.py
okb/plugins/registry.py
okb/plugins/sources/__init__.py
okb/plugins/sources/dropbox_paper.py
okb/plugins/sources/github.py
okb/rescan.py
okb/scripts/__init__.py
okb/scripts/watch.py
okb/tokens.py
okb-1.0.0.dist-info/METADATA
okb-1.0.0.dist-info/WHEEL
okb-1.0.0.dist-info/entry_points.txt
okb-1.0.0.dist-info/RECORD
