Metadata-Version: 2.3
Name: okb
Version: 1.0.0
Summary: Personal knowledge base with semantic search for LLMs
Requires-Python: >=3.11
Classifier: Programming Language :: Python :: 3
Classifier: Programming Language :: Python :: 3.11
Classifier: Programming Language :: Python :: 3.12
Classifier: Programming Language :: Python :: 3.13
Provides-Extra: all
Provides-Extra: dev
Provides-Extra: docx
Provides-Extra: llm
Provides-Extra: llm-bedrock
Provides-Extra: pdf
Provides-Extra: web
Requires-Dist: PyGithub (>=2.0.0)
Requires-Dist: anthropic (>=0.40.0) ; extra == "all"
Requires-Dist: anthropic (>=0.40.0) ; extra == "llm"
Requires-Dist: anthropic (>=0.40.0) ; extra == "llm-bedrock"
Requires-Dist: boto3 (>=1.28.0) ; extra == "llm-bedrock"
Requires-Dist: botocore (>=1.31.0) ; extra == "llm-bedrock"
Requires-Dist: click (>=8.0.0)
Requires-Dist: dropbox (>=12.0.0)
Requires-Dist: einops (>=0.7.0)
Requires-Dist: mcp (>=1.0.0)
Requires-Dist: modal (>=1.0.0)
Requires-Dist: pgvector (>=0.2.0)
Requires-Dist: psycopg[binary] (>=3.1.0)
Requires-Dist: pymupdf (>=1.23.0) ; extra == "all"
Requires-Dist: pymupdf (>=1.23.0) ; extra == "pdf"
Requires-Dist: pytest (>=7.0.0) ; extra == "dev"
Requires-Dist: python-docx (>=1.1.0) ; extra == "all"
Requires-Dist: python-docx (>=1.1.0) ; extra == "docx"
Requires-Dist: pyyaml (>=6.0)
Requires-Dist: ruff (>=0.1.0) ; extra == "dev"
Requires-Dist: sentence-transformers (>=2.2.0)
Requires-Dist: trafilatura (>=1.6.0) ; extra == "all"
Requires-Dist: trafilatura (>=1.6.0) ; extra == "web"
Requires-Dist: watchdog (>=3.0.0)
Requires-Dist: yoyo-migrations (>=8.0.0)
